docs/conf.py
examples/chatdemo/__init__.py
examples/chatdemo/handlers.py
examples/chatdemows/__init__.py
examples/chatdemows/handlers.py
examples/facebook/__init__.py
examples/facebook/app.py
examples/facebook/handlers.py
examples/feed/__init__.py
examples/feed/app.py
examples/feed/handlers.py
examples/google/__init__.py
examples/google/app.py
examples/google/handlers.py
examples/launcher/__init__.py
examples/launcher/app.py
examples/launcher/handlers.py
examples/launcher/charge/__init__.py
examples/launcher/charge/app.py
examples/launcher/charge/handlers.py
examples/multiapp/__init__.py
examples/multiapp/app.py
examples/multiapp/handlers.py
examples/nosessionapp/__init__.py
examples/nosessionapp/app.py
examples/nosessionapp/handlers.py
examples/schedapp/__init__.py
examples/schedapp/app.py
examples/schedapp/handlers.py
examples/schedapp/jobs.py
examples/testapp/__init__.py
examples/testapp/app.py
examples/testapp/handlers.py
examples/testapp/models.py
examples/testapp/services.py
examples/testapp/uimodules.py
examples/testapp/components/__init__.py
examples/testapp/components/internal/__init__.py
examples/testapp/components/internal/component.py
examples/testapp/components/internal/uimodules.py
examples/testapp/management/__init__.py
examples/testapp/management/commands.py
examples/testapp/management/tasks.py
examples/twitter/__init__.py
examples/twitter/app.py
examples/twitter/handlers.py
firenado/__init__.py
firenado/config.py
firenado/data.py
firenado/launcher.py
firenado/schedule.py
firenado/security.py
firenado/service.py
firenado/session.py
firenado/sqlalchemy.py
firenado/testing.py
firenado/tornadoweb.py
firenado/uimodules.py
firenado/bin/__init__.py
firenado/bin/firenado-cli.py
firenado/bin/firenado-cli1.py
firenado/cli/__init__.py
firenado/cli/commands.py
firenado/cli/root.py
firenado/components/__init__.py
firenado/components/firenado/__init__.py
firenado/components/firenado/component.py
firenado/components/firenado/handlers.py
firenado-0.9.6.dist-info/licenses/LICENSE
firenado-0.9.6.dist-info/METADATA
firenado-0.9.6.dist-info/WHEEL
firenado-0.9.6.dist-info/entry_points.txt
firenado-0.9.6.dist-info/top_level.txt
firenado-0.9.6.dist-info/RECORD
