Metadata-Version: 2.4
Name: firenado
Version: 0.9.6
Summary: Firenado is a python web framework based on Tornado web framework/server.
Author-email: Flavio Garcia <piraz@candango.org>
Maintainer-email: Flavio Garcia <piraz@candango.org>
License-Expression: Apache-2.0
Project-URL: Homepage, https://github.com/candango/firenado
Classifier: Development Status :: 5 - Production/Stable
Classifier: Environment :: Console
Classifier: Environment :: Web Environment
Classifier: Operating System :: OS Independent
Classifier: Programming Language :: Python
Classifier: Programming Language :: Python :: 3.9
Classifier: Programming Language :: Python :: 3.10
Classifier: Programming Language :: Python :: 3.11
Classifier: Programming Language :: Python :: 3.12
Classifier: Programming Language :: Python :: 3.13
Classifier: Programming Language :: Python :: 3 :: Only
Classifier: Topic :: Internet :: WWW/HTTP
Classifier: Topic :: Internet :: WWW/HTTP :: Dynamic Content
Classifier: Topic :: Internet :: WWW/HTTP :: WSGI
Classifier: Topic :: Software Development :: Libraries :: Application Frameworks
Classifier: Topic :: Software Development :: Libraries :: Python Modules
Requires-Python: >=3.9
License-File: LICENSE
Requires-Dist: cartola==0.21
Requires-Dist: click==8.1.7
Requires-Dist: pyyaml==6.0.3
Requires-Dist: taskio==0.0.7
Requires-Dist: tornado==6.5.2
Provides-Extra: all
Requires-Dist: croniter==6.0.0; extra == "all"
Requires-Dist: greenlet==3.2.2; extra == "all"
Requires-Dist: hiredis==3.3.0; extra == "all"
Requires-Dist: pexpect==4.9.0; extra == "all"
Requires-Dist: ptyprocess==0.7.0; extra == "all"
Requires-Dist: python-dateutil==2.9.0.post0; extra == "all"
Requires-Dist: pytz==2025.2; extra == "all"
Requires-Dist: redis==7.0.1; extra == "all"
Requires-Dist: six==1.17.0; extra == "all"
Requires-Dist: sqlalchemy==2.0.44; extra == "all"
Requires-Dist: typing-extensions==4.13.2; extra == "all"
Provides-Extra: redis
Requires-Dist: hiredis==3.3.0; extra == "redis"
Requires-Dist: redis==7.0.1; extra == "redis"
Provides-Extra: pexpect
Requires-Dist: pexpect==4.9.0; extra == "pexpect"
Requires-Dist: ptyprocess==0.7.0; extra == "pexpect"
Provides-Extra: schedule
Requires-Dist: croniter==6.0.0; extra == "schedule"
Requires-Dist: python-dateutil==2.9.0.post0; extra == "schedule"
Requires-Dist: pytz==2025.2; extra == "schedule"
Requires-Dist: six==1.17.0; extra == "schedule"
Provides-Extra: sqlalchemy
Requires-Dist: greenlet==3.2.2; extra == "sqlalchemy"
Requires-Dist: sqlalchemy==2.0.44; extra == "sqlalchemy"
Requires-Dist: typing-extensions==4.13.2; extra == "sqlalchemy"
Dynamic: license-file
